latex/__init__.py
latex/table_image_utils.py
hw2latexutils-0.1.0.dist-info/METADATA
hw2latexutils-0.1.0.dist-info/WHEEL
hw2latexutils-0.1.0.dist-info/top_level.txt
hw2latexutils-0.1.0.dist-info/RECORD
