Metadata-Version: 2.4
Name: hw2latexutils
Version: 0.1.0
Summary: LaTeX table and image generation library for HW2
Author-email: Nikita Rakcheev <nrakcheev4@gmail.com>
Requires-Python: >=3.12
